bht.v
`default_nettype none

module bht (
    input wire clk, rst,
    // Read Ports[IF]
    input wire [31:0] read_pc,
    output wire predict_taken,
    // Write Ports[EX]
    input wire updated_en,
    input [31:0] updated_pc,
    input wire branch_taken
);
    reg [1:0] bht_table [0:63];
    integer i;

    wire [5:0] read_index    = read_pc [5:0];
    wire [5:0] updated_index = updated_pc [5:0];

    // If MSB of the state is 1 then prediction is 1 else it is 0
    assign predict_taken = bht_table[read_index][1];

    always @(posedge clk) begin
        if (rst) begin
            for (i = 0; i < 64; i=i+1) begin
                // Initialize to Weakly Not Taken
                // If taken goes to 10, else goes to 00
                bht_table[i] <= 2'b01;
            end
        end
        else if (updated_en) begin
            if (branch_taken) begin
                // 
                bht_table[updated_index] <= (bht_table[updated_index] == 2'b11) ? 2'b11 : bht_table[updated_index] + 1'b1;
            end
            else begin
                bht_table[updated_index] <= (bht_table[updated_index] == 2'b00) ? 2'b00 : bht_table[updated_index] - 1'b1;
            end
        end
    end
endmodule

btb.v
`default_nettype none

module btb (
    input wire clk, rst,
    // Read Ports[IF]
    input wire [31:0] read_pc,
    output wire btb_hit,
    output wire [31:0] predicted_target,
    // Write Ports[EX]
    input wire updated_en,
    input wire [31:0] updated_pc, actual_target
);
    reg [31:0] target_table [0:63];
    reg [25:0] tag_table [0:63];
    reg valid_table [0:63];
    integer i;

    wire [5:0]  read_index    = read_pc [5:0];
    wire [5:0]  updated_index = updated_pc [5:0];
    wire [25:0] read_tag      = read_pc [31:6];
    wire [25:0] updated_tag   = updated_pc [31:6];

    assign btb_hit          = valid_table[read_index] && (tag_table[read_index] == read_tag);
    assign predicted_target = target_table[read_index];

    always @(posedge clk) begin
        if(rst) begin
            for (i = 0; i<64; i=i+1) begin
                valid_table[i]  <= 1'b0;
                tag_table[i]    <= 26'b0;
                target_table[i] <= 32'b0;
            end
        end
        else if (updated_en) begin
            valid_table[updated_index]  <= 1'b1;
            tag_table[updated_index]    <= updated_tag;
            target_table[updated_index] <= actual_target;
        end
    end
endmodule

processor.v
`default_nettype none

module MIPS32_pipeline (
    input clk,
    input rst              // Active high synchronous reset
);
    integer i;
    // Between Instruction Fetch and Instruction Decode Stages
    reg [31:0] PC, IF_ID_IR, IF_ID_NPC;
    reg [31:0] IF_ID_PC, IF_ID_pred_target;    // Tracking PC for predection acrosee stages
    reg IF_ID_pred_taken;

    // Between Instruction Decode and Execution Stages
    reg [31:0] ID_EX_IR, ID_EX_NPC, ID_EX_A, ID_EX_B, ID_EX_Imm;
    reg [2:0]  ID_EX_type, EX_MEM_type, MEM_WB_type;
    reg ID_EX_RegWrite;                        // for Data Hazard
    reg [31:0] ID_EX_PC, ID_EX_pred_target;
    reg ID_EX_pred_taken;

    // Between Execution and Memory Stages
    reg [31:0] EX_MEM_IR, EX_MEM_ALUOut, EX_MEM_B;
    reg  EX_MEM_cond;
    reg EX_MEM_RegWrite;                       // for Data Hazard

    // Between Memory and Write Back Stages
    reg [31:0] MEM_WB_IR, MEM_WB_ALUOut, MEM_WB_LMD;
    reg MEM_WB_RegWrite;                       // for Data Hazard

    reg [31:0] RegBank [0:31];                 // Register Bank(32 x 32)
    reg [31:0] Mem [0:1023];                   // 1024 x 32 memory  

    // r - type and i - type instructions
    parameter ADD = 6'b000000, SUB = 6'b000001, AND  = 6'b000010, OR   = 6'b000011, SLT  = 6'b000100, MUL   = 6'b000101, HLT  = 6'b111111,
              LW  = 6'b001000, SW  = 6'b001001, ADDI = 6'b001010, SUBI = 6'b001011, SLTI = 6'b001100, BNEQZ = 6'b001101, BEQZ = 6'b001110,
              NOOPR = 6'b101100;
    
    // Types of instructions
    parameter RR_ALU = 3'b000, RM_ALU = 3'b001, LOAD = 3'b010, STORE = 3'b011, BRANCH = 3'b100, HALT = 3'b101;
    parameter NOP = 3'd110;                    // For Hazards

    reg HALTED;                                // Set after HLT instruction is completed

    // Branch Prediction Wires and Registers
    wire btb_hit;
    wire [31:0] predicted_target;
    wire predict_taken;

    // Misprediction Evaluation Signals in EX Stage
    wire actual_branch_taken;
    wire [31:0] actual_target_val;
    wire misprediction;
    wire [31:0] corrected_pc;
    wire btb_bht_update_en;

    // Destination Registers fo forwarding
    reg [4:0] ID_EX_Dest;
    reg [4:0] EX_MEM_Dest;
    reg [4:0] MEM_WB_Dest;

    // If hazard occurs for load instruction
    wire load_stall;
    assign load_stall = (ID_EX_type == LOAD) && ((ID_EX_IR[20:16] == IF_ID_IR[25:21]) || (ID_EX_IR[20:16] == IF_ID_IR[20:16])) && (ID_EX_IR[20:16] != 5'b00000);

    // Early Halt Detection
    wire stop_fetch;
    assign stop_fetch = (IF_ID_IR[31:26] == HLT) || (ID_EX_type == HALT) || (EX_MEM_type == HALT) || (MEM_WB_type == HALT) || HALTED;

    // Combinational WB to ID Register Forwarding
    wire [31:0] wb_data = (MEM_WB_type == LOAD) ? MEM_WB_LMD : MEM_WB_ALUOut;
    wire [31:0] rs_data = (IF_ID_IR[25:21] == 5'b00000) ? 32'h00000000 : 
                          (MEM_WB_RegWrite && (MEM_WB_Dest == IF_ID_IR[25:21])) ? wb_data : 
                          RegBank[IF_ID_IR[25:21]];
                          
    wire [31:0] rt_data = (IF_ID_IR[20:16] == 5'b00000) ? 32'h00000000 : 
                          (MEM_WB_RegWrite && (MEM_WB_Dest == IF_ID_IR[20:16])) ? wb_data : 
                          RegBank[IF_ID_IR[20:16]];

    // Instantiate bht and btb modules
    btb u_btb (
        .clk(clk),
        .rst(rst),
        .read_pc(PC),
        .btb_hit(btb_hit),
        .predicted_target(predicted_target),
        .updated_en(btb_bht_update_en),
        .updated_pc(ID_EX_PC),
        .actual_target(actual_target_val)
    );

    bht u_bht (
        .clk(clk),
        .rst(rst),
        .read_pc(PC),
        .predict_taken(predict_taken),
        .updated_en(btb_bht_update_en),
        .updated_pc(ID_EX_PC),
        .branch_taken(actual_branch_taken)
    );
    

    // Instruction Fetch[IF] Stage
    always @(posedge clk) begin
        if (rst) begin
            PC                <= 32'h00000000;  // Reset Address
            IF_ID_IR          <= {NOOPR,26'b0}; // No operation
            IF_ID_NPC         <= 32'h00000000;
            IF_ID_PC          <= 32'h00000000;
            IF_ID_pred_taken  <= 1'b0;
            IF_ID_pred_target <= 32'h00000000;
        end
        else if(misprediction) begin
            PC                <= corrected_pc;
            IF_ID_IR          <= {NOOPR,26'b0}; // Flush with NOP
            IF_ID_NPC         <= 32'h00000000;
            IF_ID_PC          <= 32'h00000000;
            IF_ID_pred_taken  <= 1'b0;
            IF_ID_pred_target <= 32'h00000000;
        end
        else if(load_stall) begin
            PC        <= PC;
            IF_ID_IR  <= IF_ID_IR;
            IF_ID_NPC <= IF_ID_NPC;
            IF_ID_PC          <= IF_ID_PC;
            IF_ID_pred_taken  <= IF_ID_pred_taken;
            IF_ID_pred_target <= IF_ID_pred_target;
        end
        else if (HALTED == 0) begin
            if (stop_fetch) begin
                // Freeze PC and inject NOPs behind the HLT instruction 
                PC                <= PC;
                IF_ID_IR          <= {NOOPR,26'b0};
                IF_ID_NPC         <= IF_ID_NPC;
                IF_ID_PC          <= IF_ID_PC;
                IF_ID_pred_taken  <= 1'b0;
                IF_ID_pred_target <= 32'h00000000;
            end else begin
                IF_ID_IR          <= Mem[PC];
                IF_ID_NPC         <= PC + 1;
                IF_ID_PC          <= PC;
                IF_ID_pred_taken  <= btb_hit && predict_taken;
                IF_ID_pred_target <= predicted_target;
                
                // Next PC Generation
                if (btb_hit && predict_taken) begin
                    PC <= predicted_target;
                end else begin
                    PC <= PC + 1;
                end
            end
        end
    end

    // Instruction Decode[ID] Stage
    always @(posedge clk) begin
        if (rst) begin
            ID_EX_A           <= 32'h00000000;
            ID_EX_B           <= 32'h00000000;
            ID_EX_NPC         <= 32'h00000000;
            ID_EX_IR          <= 32'h00000000;
            ID_EX_Imm         <= 32'h00000000;
            ID_EX_type        <= NOP;               
            ID_EX_RegWrite    <= 1'b0;
            ID_EX_Dest        <= 5'b00000;
            ID_EX_PC          <= 32'h00000000;
            ID_EX_pred_taken  <= 1'b0;
            ID_EX_pred_target <= 32'h00000000;
        end
        else if (misprediction) begin
            // Flush ID/EX register because this instruction is from the wrong spec path
            ID_EX_A           <= 32'h00000000;
            ID_EX_B           <= 32'h00000000;
            ID_EX_NPC         <= 32'h00000000;
            ID_EX_IR          <= 32'h00000000;
            ID_EX_Imm         <= 32'h00000000;
            ID_EX_type        <= NOP;
            ID_EX_RegWrite    <= 1'b0;
            ID_EX_Dest        <= 5'b00000;
            ID_EX_PC          <= 32'h00000000;
            ID_EX_pred_taken  <= 1'b0;
            ID_EX_pred_target <= 32'h00000000;
        end
        else if(load_stall) begin
            ID_EX_RegWrite <= 0;
            ID_EX_type     <= NOP;
        end
        else if (HALTED == 0) begin
            ID_EX_A <= rs_data;
            ID_EX_B <= rt_data;

            ID_EX_NPC         <= IF_ID_NPC;
            ID_EX_IR          <= IF_ID_IR;
            ID_EX_Imm         <= {{16{IF_ID_IR[15]}}, {IF_ID_IR[15 : 0]}};
            ID_EX_PC          <= IF_ID_PC;
            ID_EX_pred_taken  <= IF_ID_pred_taken;
            ID_EX_pred_target <= IF_ID_pred_target;

            case (IF_ID_IR[31 : 26])
                ADD, SUB, AND, OR, MUL, SLT : begin
                    ID_EX_type     <= RR_ALU;
                    ID_EX_RegWrite <= 1'b1;
                    ID_EX_Dest     <= IF_ID_IR[15:11];
                end 
                ADDI, SUBI, SLTI            : begin
                    ID_EX_type     <= RM_ALU;
                    ID_EX_RegWrite <= 1'b1;
                    ID_EX_Dest     <= IF_ID_IR[20:16];
                end 
                LW                          : begin
                    ID_EX_type     <= LOAD;
                    ID_EX_RegWrite <= 1'b1;
                    ID_EX_Dest     <= IF_ID_IR[20:16];
                end
                SW                          : begin
                    ID_EX_type     <= STORE;
                    ID_EX_RegWrite <= 1'b0;
                    ID_EX_Dest     <= 5'b00000;
                end
                BNEQZ, BEQZ                 : begin
                    ID_EX_type     <= BRANCH;
                    ID_EX_RegWrite <= 1'b0;
                    ID_EX_Dest     <= 5'b00000;
                end
                HLT                         : begin
                    ID_EX_type     <= HALT;
                    ID_EX_RegWrite <= 1'b0;
                    ID_EX_Dest     <= 5'b00000;
                end
                default                     : begin
                    ID_EX_type     <= NOP;
                    ID_EX_RegWrite <= 1'b0;
                    ID_EX_Dest     <= 5'b00000;
                end
            endcase
        end
    end

    // Execution[EX] Stage
    assign actual_branch_taken = (ID_EX_IR [31:26] == BEQZ) ? (forwardA == 32'h0) : (ID_EX_IR [31:26] == BNEQZ) ? (forwardA != 32'h0) : 1'b0;
    assign actual_target_val = ID_EX_NPC + ID_EX_Imm;
    // misprediction when the prediction is wrong or the prediction is correct but the address is wrong
    assign misprediction = (ID_EX_type == BRANCH) && ((ID_EX_pred_taken != actual_branch_taken) || (actual_branch_taken && (ID_EX_pred_target != actual_target_val)));
    assign corrected_pc = actual_branch_taken ? actual_target_val : ID_EX_NPC;
    //Enabling
    assign btb_bht_update_en = (ID_EX_type == BRANCH) && (HALTED == 0);
    // Forwarding Unit
    reg[31 : 0] forwardA, forwardB;
    always @(*) begin
        // default values in registers A and B
        forwardA = ID_EX_A;
        forwardB = ID_EX_B;

        // Forward A(rs)
        // EX Hazard
        if(EX_MEM_RegWrite && (EX_MEM_Dest != 5'b00000) && (EX_MEM_Dest == ID_EX_IR[25 : 21])) begin
            forwardA = EX_MEM_ALUOut;
        end
        // Mem Hazard
        else if(MEM_WB_RegWrite && (MEM_WB_Dest != 5'b00000) && (MEM_WB_Dest == ID_EX_IR[25 : 21])) begin
            forwardA = (MEM_WB_type == LOAD) ? MEM_WB_LMD : MEM_WB_ALUOut;
        end

        // Forward B(rt)
        // EX Hazard
        if (EX_MEM_RegWrite && (EX_MEM_Dest != 5'b00000) && (EX_MEM_Dest == ID_EX_IR[20 : 16])) begin
            forwardB = EX_MEM_ALUOut;
        end
        // Mem Hazard
        else if (MEM_WB_RegWrite && (MEM_WB_Dest != 5'b00000) && (MEM_WB_Dest == ID_EX_IR[20 : 16])) begin
            forwardB = (MEM_WB_type == LOAD) ? MEM_WB_LMD : MEM_WB_ALUOut; 
        end
    end
    
    always @(posedge clk) begin
        if (rst) begin
            EX_MEM_type     <= NOP;
            EX_MEM_IR       <= 32'h00000000;
            EX_MEM_ALUOut   <= 32'h00000000;
            EX_MEM_B        <= 32'h00000000;
            EX_MEM_cond     <= 1'b0;
            EX_MEM_RegWrite <= 1'b0;
            EX_MEM_Dest     <= 5'b00000;
        end
        else if (HALTED == 0) begin
            EX_MEM_type     <= ID_EX_type;
            EX_MEM_IR       <= ID_EX_IR;
            EX_MEM_RegWrite <= ID_EX_RegWrite;
            EX_MEM_Dest     <= ID_EX_Dest;

            case (ID_EX_type)
                RR_ALU : begin
                    case (ID_EX_IR[31 : 26])
                        ADD : EX_MEM_ALUOut <= forwardA + forwardB;
                        SUB : EX_MEM_ALUOut <= forwardA - forwardB;
                        AND : EX_MEM_ALUOut <= forwardA & forwardB; 
                        OR  : EX_MEM_ALUOut <= forwardA | forwardB; 
                        SLT : EX_MEM_ALUOut <= forwardA < forwardB; 
                        MUL : EX_MEM_ALUOut <= forwardA * forwardB;  
                        default: EX_MEM_ALUOut <= 32'hxxxxxxxx;
                    endcase
                end

                RM_ALU : begin
                    case (ID_EX_IR[31 : 26])
                        ADDI : EX_MEM_ALUOut <= forwardA + ID_EX_Imm; 
                        SUBI : EX_MEM_ALUOut <= forwardA - ID_EX_Imm; 
                        SLTI : EX_MEM_ALUOut <= forwardA < ID_EX_Imm; 
                        default: EX_MEM_ALUOut <= 32'hxxxxxxxx;
                    endcase
                end

                LOAD, STORE : begin
                    EX_MEM_ALUOut <= forwardA + ID_EX_Imm;
                    EX_MEM_B      <= forwardB;
                end

                BRANCH : begin
                    EX_MEM_ALUOut <= ID_EX_NPC + ID_EX_Imm;
                    EX_MEM_cond   <= (forwardA == 0);
                end 
            endcase
        end
    end

    // Memory[MEM] Stage
    always @(posedge clk) begin
        if (rst) begin
            MEM_WB_type     <= NOP;
            MEM_WB_IR       <= 32'h00000000;
            MEM_WB_ALUOut   <= 32'h00000000;
            MEM_WB_LMD      <= 32'h00000000;
            MEM_WB_RegWrite <= 1'b0;
            MEM_WB_Dest     <= 5'b00000;
        end
        else if (HALTED == 0) begin
            MEM_WB_type     <= EX_MEM_type;
            MEM_WB_IR       <= EX_MEM_IR;
            MEM_WB_RegWrite <= EX_MEM_RegWrite;
            MEM_WB_Dest     <= EX_MEM_Dest;

            case (EX_MEM_type)
                RR_ALU, RM_ALU : MEM_WB_ALUOut <= EX_MEM_ALUOut;
                LOAD           : MEM_WB_LMD    <= Mem[EX_MEM_ALUOut];
                STORE          : Mem[EX_MEM_ALUOut] <= EX_MEM_B;
                default: ;
            endcase
        end
    end

    // Write Back[WB] Stage
    always @(posedge clk) begin
        if (rst) begin
            HALTED <= 1'b0;
            // Clear all registers in the Register Bank to prevent simulation 'X' states
            for (i = 0; i < 32; i = i + 1) begin
                RegBank[i] <= 32'h00000000;
            end
        end
        else if (MEM_WB_RegWrite && (MEM_WB_Dest != 5'b00000)) begin
            RegBank[MEM_WB_Dest] <= (MEM_WB_type == LOAD) ? MEM_WB_LMD : MEM_WB_ALUOut;
        end
        else if (MEM_WB_type == HALT) begin
            HALTED <= 1'b1;
        end      
    end
endmodule

tb.v
module test_MIPS32;

    reg clk1, rst;
    integer k;

    MIPS32_pipeline mips(clk1, rst);

    // Clock Generation
    initial begin
        clk1 = 0;
        rst = 0;

        forever begin
            #5 clk1 = 1;
            #5 clk1 = 0;
        end
    end

    task reset_cpu;
    begin
        rst = 1;
        #20;
        rst = 0;

        mips.PC = 0;
        mips.HALTED = 0;
    end
    endtask

    // Program 1
    task load_program1;
    begin
        // Initialize Register Bank
        for (k = 0; k < 31; k = k + 1)
            mips.RegBank[k] = k;

        // Load Program into Memory
        mips.Mem[0] = 32'h2801000a; // ADDI R1, R0, 10
        mips.Mem[1] = 32'h28020014; // ADDI R2, R0, 20
        mips.Mem[2] = 32'h28030019; // ADDI R3, R0, 25
        mips.Mem[3] = 32'h00222000; // AND R4, R1, R2
        mips.Mem[4] = 32'h00832800; // AND R5, R4, R3
        mips.Mem [7]= 32'hfc000000; // HLT

        // Initialize Processor
        mips.HALTED = 0;
        mips.PC = 0;
    end
    endtask

    // Program 2
    task load_program2;
    begin
        // Initialize Register Bank
        for (k = 0; k < 31; k = k + 1)
            mips.RegBank[k] = k;

        // Load Program into Memory
        mips.Mem[0] = 32'h28010078; // ADDI R1, R0, 120
        mips.Mem[1] = 32'h20220000; // LW R2, 0(R1)
        mips.Mem[2] = 32'h2842002d; // ADDI R2, R2, 45
        mips.Mem[3] = 32'h24220001; // SW R2, 1(R1)
        mips.Mem [7]= 32'hfc000000; // HLT

        // Data Memory
        mips.Mem[120] = 85;

        // Initialize Processor
        mips.PC = 0;
        mips.HALTED = 0;
    end
    endtask

    // Program 3 
    task load_program3;
    begin
        // Initialize Register Bank
        for (k = 0; k < 31; k = k + 1)
            mips.RegBank[k] = k;

        // Load Program into Memory
        mips.Mem [0] = 32'h280a00c8; // ADDI R10, R0, 200
        mips.Mem [1] = 32'h28020001; // ADDI R2, R0, 1
        mips.Mem [2] = 32'h21430000; // LW R3, 0(R10)
        mips.Mem [3] = 32'h14431000; // LOOP : MUL R2, R2, R3
        mips.Mem [4] = 32'h2c630001; // SUBI R3, R3, 1
        mips.Mem [5] = 32'h3460fffd; // BNEQZ R3, LOOP ( offset -3)
        mips.Mem [6] = 32'h2542fffe; // SW R2, -2(R10)
        mips.Mem [7] = 32'hfc000000; // HLT

        // Data Memory
        mips.Mem[200] = 7;

        // Initialize Processor
        mips.PC = 0;
        mips.HALTED = 0;
    end
    endtask


    initial begin

        // Execute Program 1
        reset_cpu();
        load_program1();

        #280;
        for (k = 0; k < 6; k = k + 1)
            $display("R%1d = %2d", k, mips.RegBank[k]);

        // Execute Program 2
        reset_cpu();
        load_program2();

        #500;
        $display("Mem[120] = %4d", mips.Mem[120]);
        $display("Mem[121] = %4d", mips.Mem[121]);

        // Execute Program 3
        reset_cpu();
        load_program3();

        #2000;
        $display("Mem[200] = %2d", mips.Mem[200]);
        $display("Mem[198] = %6d", mips.Mem[198]);
    end

    // Dump Waveforms
    initial begin
        $dumpfile("mips.vcd");
        $dumpvars(0, test_MIPS32);
        // $monitor("R2 : %4d", mips.RegBank[2]);
    end

    
    // Finish Simulation
    initial begin
        #3000 $finish;
    end

endmodule

mips.vcd
$date
	Mon Jun 22 17:40:16 2026
$end
$version
	Icarus Verilog
$end
$timescale
	1s
$end
$scope module test_MIPS32 $end
$var reg 1 ! clk1 $end
$var reg 1 " rst $end
$var integer 32 # k [31:0] $end
$scope module mips $end
$var wire 1 $ btb_bht_update_en $end
$var wire 1 ! clk $end
$var wire 1 % load_stall $end
$var wire 1 & misprediction $end
$var wire 1 " rst $end
$var wire 1 ' stop_fetch $end
$var wire 32 ( wb_data [31:0] $end
$var wire 32 ) rt_data [31:0] $end
$var wire 32 * rs_data [31:0] $end
$var wire 32 + predicted_target [31:0] $end
$var wire 1 , predict_taken $end
$var wire 32 - corrected_pc [31:0] $end
$var wire 1 . btb_hit $end
$var wire 32 / actual_target_val [31:0] $end
$var wire 1 0 actual_branch_taken $end
$var reg 32 1 EX_MEM_ALUOut [31:0] $end
$var reg 32 2 EX_MEM_B [31:0] $end
$var reg 5 3 EX_MEM_Dest [4:0] $end
$var reg 32 4 EX_MEM_IR [31:0] $end
$var reg 1 5 EX_MEM_RegWrite $end
$var reg 1 6 EX_MEM_cond $end
$var reg 3 7 EX_MEM_type [2:0] $end
$var reg 1 8 HALTED $end
$var reg 32 9 ID_EX_A [31:0] $end
$var reg 32 : ID_EX_B [31:0] $end
$var reg 5 ; ID_EX_Dest [4:0] $end
$var reg 32 < ID_EX_IR [31:0] $end
$var reg 32 = ID_EX_Imm [31:0] $end
$var reg 32 > ID_EX_NPC [31:0] $end
$var reg 32 ? ID_EX_PC [31:0] $end
$var reg 1 @ ID_EX_RegWrite $end
$var reg 1 A ID_EX_pred_taken $end
$var reg 32 B ID_EX_pred_target [31:0] $end
$var reg 3 C ID_EX_type [2:0] $end
$var reg 32 D IF_ID_IR [31:0] $end
$var reg 32 E IF_ID_NPC [31:0] $end
$var reg 32 F IF_ID_PC [31:0] $end
$var reg 1 G IF_ID_pred_taken $end
$var reg 32 H IF_ID_pred_target [31:0] $end
$var reg 32 I MEM_WB_ALUOut [31:0] $end
$var reg 5 J MEM_WB_Dest [4:0] $end
$var reg 32 K MEM_WB_IR [31:0] $end
$var reg 32 L MEM_WB_LMD [31:0] $end
$var reg 1 M MEM_WB_RegWrite $end
$var reg 3 N MEM_WB_type [2:0] $end
$var reg 32 O PC [31:0] $end
$var reg 32 P forwardA [31:0] $end
$var reg 32 Q forwardB [31:0] $end
$var integer 32 R i [31:0] $end
$scope module u_bht $end
$var wire 1 0 branch_taken $end
$var wire 1 ! clk $end
$var wire 32 S read_pc [31:0] $end
$var wire 1 " rst $end
$var wire 1 $ updated_en $end
$var wire 32 T updated_pc [31:0] $end
$var wire 6 U updated_index [5:0] $end
$var wire 6 V read_index [5:0] $end
$var wire 1 , predict_taken $end
$var integer 32 W i [31:0] $end
$upscope $end
$scope module u_btb $end
$var wire 32 X actual_target [31:0] $end
$var wire 1 . btb_hit $end
$var wire 1 ! clk $end
$var wire 32 Y predicted_target [31:0] $end
$var wire 32 Z read_pc [31:0] $end
$var wire 1 " rst $end
$var wire 1 $ updated_en $end
$var wire 32 [ updated_pc [31:0] $end
$var wire 26 \ updated_tag [25:0] $end
$var wire 6 ] updated_index [5:0] $end
$var wire 26 ^ read_tag [25:0] $end
$var wire 6 _ read_index [5:0] $end
$var integer 32 ` i [31:0] $end
$upscope $end
$upscope $end
$scope task load_program1 $end
$upscope $end
$scope task load_program2 $end
$upscope $end
$scope task load_program3 $end
$upscope $end
$scope task reset_cpu $end
$upscope $end
$upscope $end
$enddefinitions $end
#0
$dumpvars
bx `
bx _
bx ^
bx ]
bx \
bx [
bx Z
bx Y
bx X
bx W
bx V
bx U
bx T
bx S
bx R
bx Q
bx P
bx O
bx N
xM
bx L
bx K
bx J
bx I
bx H
xG
bx F
bx E
bx D
bx C
bx B
xA
x@
bx ?
bx >
bx =
bx <
bx ;
bx :
bx 9
x8
bx 7
x6
x5
bx 4
bx 3
bx 2
bx 1
x0
bx /
x.
bx -
x,
bx +
bx *
bx )
bx (
x'
x&
x%
x$
bx #
1"
0!
$end
#5
0'
b0 *
b0 )
0,
0.
0%
00
b0 V
b0 +
b0 Y
b0 _
b0 ^
b0 U
b0 ]
b0 \
0&
b0 -
b0 Q
b0 P
b0 (
0$
b0 H
0G
b0 F
b0 E
b10110000000000000000000000000000 D
b0 O
b0 S
b0 Z
b0 B
0A
b0 ?
b0 T
b0 [
b0 ;
0@
b110 C
b0 /
b0 X
b0 =
b0 <
b0 >
b0 :
b0 9
b0 3
05
06
b0 2
b0 1
b0 4
b110 7
b0 J
0M
b0 L
b0 I
b0 K
b110 N
08
b1000000 `
b1000000 W
b100000 R
1!
#10
0!
#15
b100000 R
b1000000 W
b1000000 `
1!
#20
0!
b11111 #
0"
#25
b1 )
b1 V
b1 _
b1 O
b1 S
b1 Z
b1 E
b101000000000010000000000001010 D
b10110000000000000000000000000000 <
1!
#30
0!
#35
b10 )
b1 -
b1 Q
b10 V
b10 _
b10110000000000000000000000000000 4
b1 ;
1@
b1 C
b1010 =
b101000000000010000000000001010 <
b1011 /
b1011 X
b1 >
b1 :
b10 O
b10 S
b10 Z
b1 F
b10 E
b101000000000100000000000010100 D
1!
#40
0!
#45
b11 )
b11 V
b11 _
b1 U
b1 ]
b10 -
b10 Q
b11 O
b11 S
b11 Z
b10 F
b11 E
b101000000000110000000000011001 D
b10 ;
b1 ?
b1 T
b1 [
b10100 =
b101000000000100000000000010100 <
b10110 /
b10110 X
b10 >
b10 :
b1010 1
b1 3
15
b101000000000010000000000001010 4
b1 7
b10110000000000000000000000000000 K
1!
#50
0!
#55
b10 )
b1010 *
b1010 (
b10 U
b10 ]
b11 -
b11 Q
b100 V
b100 _
b1010 I
b1 J
1M
b101000000000010000000000001010 K
b1 N
b10100 1
b10 3
b101000000000100000000000010100 4
b11 ;
b10 ?
b10 T
b10 [
b11001 =
b101000000000110000000000011001 <
b11100 /
b11100 X
b11 >
b11 :
b100 O
b100 S
b100 Z
b11 F
b100 E
b1000100010000000000000 D
1!
#60
0!
#65
b100 *
b11 )
b101 V
b101 _
b11 U
b11 ]
b100 -
b10100 (
b10100 Q
b1010 P
b101 O
b101 S
b101 Z
b100 F
b101 E
b100000110010100000000000 D
b100 ;
b0 C
b11 ?
b11 T
b11 [
b10000000000000 =
b1000100010000000000000 <
b10000000000100 /
b10000000000100 X
b100 >
b10 :
b1010 9
b11001 1
b11 3
b101000000000110000000000011001 4
b10100 I
b10 J
b101000000000100000000000010100 K
1!
#70
0!
#75
x'
bx *
bx )
b11001 (
b100 U
b100 ]
b101 -
b11001 Q
b11110 P
b110 V
b110 _
b11001 I
b11 J
b101000000000110000000000011001 K
b11110 1
b100 3
b1000100010000000000000 4
b0 7
b101 ;
b100 ?
b100 T
b100 [
b10100000000000 =
b100000110010100000000000 <
b10100000000101 /
b10100000000101 X
b101 >
b11 :
b100 9
b110 O
b110 S
b110 Z
b101 F
b110 E
bx D
1!
#80
0!
#85
x0
b111 V
b111 _
b101 U
b101 ]
bx -
b11110 (
bx Q
bx P
b111 O
b111 S
b111 Z
b110 F
b111 E
b0 ;
0@
b110 C
b101 ?
b101 T
b101 [
bx =
bx <
bx /
bx X
b110 >
bx :
bx 9
b110111 1
b101 3
b100000110010100000000000 4
b11110 I
b100 J
b1000100010000000000000 K
b0 N
1!
#90
0!
#95
1'
b0 *
b0 )
b110111 (
b110 U
b110 ]
b1000 V
b1000 _
b110111 I
b101 J
b100000110010100000000000 K
b0 3
05
bx 4
b110 7
b110 ?
b110 T
b110 [
b111 >
b1000 O
b1000 S
b1000 Z
b111 F
b1000 E
b11111100000000000000000000000000 D
1!
#100
0!
#105
00
b111 U
b111 ]
b1000 -
b0 Q
b0 P
b10110000000000000000000000000000 D
b101 C
b111 ?
b111 T
b111 [
b1000 /
b1000 X
b0 =
b11111100000000000000000000000000 <
b1000 >
b0 :
b0 9
b0 J
0M
bx K
b110 N
1!
#110
0!
#115
b11111100000000000000000000000000 4
b101 7
b110 C
b10110000000000000000000000000000 <
1!
#120
0!
#125
b10110000000000000000000000000000 4
b110 7
b11111100000000000000000000000000 K
b101 N
1!
#130
0!
#135
18
b10110000000000000000000000000000 K
b110 N
1!
#140
0!
#145
1!
#150
0!
#155
1!
#160
0!
#165
1!
#170
0!
#175
1!
#180
0!
#185
1!
#190
0!
#195
1!
#200
0!
#205
1!
#210
0!
#215
1!
#220
0!
#225
1!
#230
0!
#235
1!
#240
0!
#245
1!
#250
0!
#255
1!
#260
0!
#265
1!
#270
0!
#275
1!
#280
0!
#285
1!
#290
0!
#295
1!
#300
0!
1"
b110 #
#305
b0 V
b0 _
b0 U
b0 ]
b0 -
b0 (
0'
b0 F
b0 E
b0 O
b0 S
b0 Z
b0 ?
b0 T
b0 [
b0 <
b0 /
b0 X
b0 >
b0 1
b0 4
b0 I
b0 K
08
b1000000 `
b1000000 W
b100000 R
1!
#310
0!
#315
b100000 R
b1000000 W
b1000000 `
1!
#320
0!
b11111 #
0"
#325
b1 )
b1 V
b1 _
b1 O
b1 S
b1 Z
b1 E
b101000000000010000000001111000 D
b10110000000000000000000000000000 <
1!
#330
0!
#335
b10 )
b1 *
b1 -
b1 Q
b10 V
b10 _
b10110000000000000000000000000000 4
b1 ;
1@
b1 C
b1111000 =
b101000000000010000000001111000 <
b1111001 /
b1111001 X
b1 >
b1 :
b10 O
b10 S
b10 Z
b1 F
b10 E
b100000001000100000000000000000 D
1!
#340
0!
#345
b10 *
1%
b11 V
b11 _
b1 U
b1 ]
b10 -
b10 Q
b1111000 P
b11 O
b11 S
b11 Z
b10 F
b11 E
b101000010000100000000000101101 D
b10 ;
b10 C
b1 ?
b1 T
b1 [
b0 =
b100000001000100000000000000000 <
b10 /
b10 X
b10 >
b10 :
b1 9
b1111000 1
b1 3
15
b101000000000010000000001111000 4
b1 7
b10110000000000000000000000000000 K
1!
#350
0!
#355
0%
b1111000 (
b1111000 Q
b1111000 P
b1111000 I
b1 J
1M
b101000000000010000000001111000 K
b1 N
b10 2
b10 3
b100000001000100000000000000000 4
b10 7
b110 C
0@
1!
#360
0!
#365
b1111000 *
b1010101 )
b100 V
b100 _
b10 U
b10 ]
b11 -
b1010101 Q
b1010101 P
b1010101 (
b100 O
b100 S
b100 Z
b11 F
b100 E
b100100001000100000000000000001 D
1@
b1 C
b10 ?
b10 T
b10 [
b101101 =
b101000010000100000000000101101 <
b110000 /
b110000 X
b11 >
b10 9
05
b110 7
b1010101 L
b10 J
b100000001000100000000000000000 K
b10 N
1!
#370
0!
#375
b11 )
b100 *
b1111000 (
b11 U
b11 ]
b100 -
b10000010 Q
b1111000 P
b101 V
b101 _
0M
b110 N
b10000010 1
15
b101000010000100000000000101101 4
b1 7
b0 ;
0@
b11 C
b11 ?
b11 T
b11 [
b1 =
b100100001000100000000000000001 <
b101 /
b101 X
b100 >
b1010101 :
b1111000 9
b101 O
b101 S
b101 Z
b100 F
b101 E
b100000110010100000000000 D
1!
#380
0!
